gifcm/__init__.py
gifcm/animated_figure.py
gifcm-0.1.0.dist-info/LICENSE
gifcm-0.1.0.dist-info/METADATA
gifcm-0.1.0.dist-info/WHEEL
gifcm-0.1.0.dist-info/top_level.txt
gifcm-0.1.0.dist-info/RECORD
