Metadata-Version: 2.1
Name: gifcm
Version: 0.1.0
Summary: Easy gif animation of matplotlib figures
Author-email: Martin Schubert <mfschubert@gmail.com>
Maintainer-email: Martin Schubert <mfschubert@gmail.com>
License: MIT License
Keywords: gif,animation,matplotlib
Requires-Python: >=3.7
License-File: LICENSE
Requires-Dist: matplotlib
Requires-Dist: numpy
Provides-Extra: dev
Requires-Dist: bump-my-version ; extra == 'dev'
Requires-Dist: darglint ; extra == 'dev'
Requires-Dist: gifcm[tests] ; extra == 'dev'
Requires-Dist: pre-commit ; extra == 'dev'
Provides-Extra: tests
Requires-Dist: parameterized ; extra == 'tests'
Requires-Dist: pytest ; extra == 'tests'
